HW/MUL/2x2/Approx2x2Mul.v
/*
 *  Custom RISCV instruction for approximate multiplication
 *
 *  Copyright (C) 2024  Samir Hodzic, Veronica Kimelman, Paul Pölzl
 *
 *  Permission to use, copy, modify, and/or distribute this software for any
 *  purpose with or without fee is hereby granted, provided that the above
 *  copyright notice and this permission notice appear in all copies.
 *
 *  THE SOFTWARE IS PROVIDED "AS IS" AND THE AUTHOR DISCLAIMS ALL WARRANTIES
 *  WITH REGARD TO THIS SOFTWARE INCLUDING ALL IMPLIED WARRANTIES OF
 *  MERCHANTABILITY AND FITNESS. IN NO EVENT SHALL THE AUTHOR BE LIABLE FOR
 *  ANY SPECIAL, DIRECT, INDIRECT, OR CONSEQUENTIAL DAMAGES OR ANY DAMAGES
 *  WHATSOEVER RESULTING FROM LOSS OF USE, DATA OR PROFITS, WHETHER IN AN
 *  ACTION OF CONTRACT, NEGLIGENCE OR OTHER TORTIOUS ACTION, ARISING OUT OF
 *  OR IN CONNECTION WITH THE USE OR PERFORMANCE OF THIS SOFTWARE.
 *
 */

// Approx2x2Mul
// Implementation for approximate multiplier (Version 2) 

module Approx2x2Mul(a, b, out);
    input wire[1:0] a, b;
    output wire[3:0] out;

    wire a0b1, a1b0, a1b1;

    assign a0b1 = a[0] & b[1];
    assign a1b0 = a[1] & b[0];
    assign a1b1 = a[1] & b[1];

    assign out[0] = a0b1 & a1b0;
    assign out[1] = a0b1 ^ a1b0;
    assign out[2] = out[0] ^ a1b1;
    assign out[3] = a0b1 & a1b0;
endmodule

HW/MUL/2x2/testbench.v
// Universal testbench for the 2x2 multipliers 

`timescale 100ps/10ps // Unit of time is 100ps

module mul2x2_tb;
    reg[1:0] a, b;      // Input of DuT
    wire[3:0] out;       // Output of DuT
    reg[3:0] out_exp;   // Expected response

    reg clk, reset;                 // clock and reset are internal
    reg[31:0] vectornum, errors;    // bookkeeping variables
    reg[7:0] testvectors[15:0];      // array of testvectors

    // Instantiate the design under test:
    //Accurate2x2Mul(.a(a), .b(b), .out(out));
    Approx2x2Mul mul(.a(a), .b(b), .out(out));

    // Generate clock
    always // no sensitivity list
        begin
            clk=1; #5;
            clk=0; #5; // 5ns period
        end
    
    initial begin
        $dumpfile("mult_tbtv.vcd"); // File with simulation resuls
        $dumpvars(0, mul2x2_tb); // Select which variables are written to file
        $readmemb("testvectors.tv", testvectors); // Readvectors
        vectornum = 0; errors = 0; // Initialize
        reset = 1;
        #27; reset = 0; // Apply reset wait
    end

    // Stimuli generation:
    // apply test vectors on rising edge of clk
    always @(posedge clk)
        begin
            #1; {a, b, out_exp} = testvectors[vectornum];
        end

    // Responsechecker:
    // check results on falling edge of clk
    always @(negedge clk)
        if (~reset) // skip during reset
            begin
            if (out !== out_exp)
                begin
                    $display("Error: inputs = %b", {a, b});
                    $display(" outputs = %b (%b exp)", out, out_exp);
                    errors = errors + 1;
                end

            // increment array index and read th next testvector
            vectornum = vectornum + 1;
            if (testvectors[vectornum] === 8'bx)
                begin
                    $display("%d tests completed with %d errors", vectornum, errors);
                    $finish;    // End simulation
                end
            end
endmodule

picorv32/picosoc/HW/MUL/2x2/mul2x2.vcd
$date
	Thu May  2 10:44:09 2024
$end
$version
	Icarus Verilog
$end
$timescale
	10ps
$end
$scope module mul2x2_tb $end
$var wire 4 ! out [3:0] $end
$var reg 2 " a [1:0] $end
$var reg 2 # b [1:0] $end
$var reg 1 $ clk $end
$var reg 32 % errors [31:0] $end
$var reg 4 & out_exp [3:0] $end
$var reg 1 ' reset $end
$var reg 32 ( vectornum [31:0] $end
$scope begin genblk1 $end
$scope module mul $end
$var wire 2 ) a [1:0] $end
$var wire 1 * a0b1 $end
$var wire 1 + a1b0 $end
$var wire 1 , a1b1 $end
$var wire 2 - b [1:0] $end
$var wire 4 . out [3:0] $end
$upscope $end
$upscope $end
$upscope $end
$enddefinitions $end
$comment Show the parameter values. $end
$dumpall
$end
#0
$dumpvars
bx .
bx -
x,
x+
x*
bx )
b0 (
1'
bx &
b0 %
1$
bx #
bx "
bx !
$end
#50
0$
#100
1$
#110
b0 !
b0 .
0*
0+
0,
b0 "
b0 )
b0 #
b0 -
b0 &
#150
0$
#200
1$
#250
0$
#270
0'
#300
1$
#350
b1 (
0$
#400
1$
#410
b1 #
b1 -
#450
b10 (
0$
#500
1$
#510
b10 #
b10 -
#550
b11 (
0$
#600
1$
#610
b11 #
b11 -
#650
b100 (
0$
#700
1$
#710
b1 "
b1 )
b0 #
b0 -
#750
b101 (
0$
#800
1$
#810
b1 #
b1 -
#850
b110 (
0$
#900
1$
#910
b10 !
b10 .
1*
b10 #
b10 -
b10 &
#950
b111 (
0$
#1000
1$
#1010
b11 #
b11 -
#1050
b1000 (
0$
#1100
1$
#1110
b0 !
b0 .
0*
b10 "
b10 )
b0 #
b0 -
b0 &
#1150
b1001 (
0$
#1200
1$
#1210
b10 !
b10 .
1+
b1 #
b1 -
b10 &
#1250
b1010 (
0$
#1300
1$
#1310
b100 !
b100 .
0+
1,
b10 #
b10 -
b100 &
#1350
b1011 (
0$
#1400
1$
#1410
b110 !
b110 .
1+
b11 #
b11 -
b110 &
#1450
b1100 (
0$
#1500
1$
#1510
b0 !
b0 .
0+
0,
b11 "
b11 )
b0 #
b0 -
b0 &
#1550
b1101 (
0$
#1600
1$
#1610
b10 !
b10 .
1+
b1 #
b1 -
b10 &
#1650
b1110 (
0$
#1700
1$
#1710
b110 !
b110 .
1*
0+
1,
b10 #
b10 -
b110 &
#1750
b1111 (
0$
#1800
1$
#1810
b1001 !
b1001 .
1+
b11 #
b11 -
b1001 &
#1850
b10000 (
0$
