HW/ADD/AccurateAddOneBit.v
module AccurateAddOneBit (A, B, Cin, Cout, Sum);

    input  wire A;
    input  wire B;
    input  wire Cin;
    output wire Cout;
    output wire Sum;

    assign Sum  = (A ^ B) ^ Cin;
    assign Cout = (A & B) | ((A ^ B) & Cin);
    
endmodule

HW/ADD/tb_SingleBit.v
`timescale 1ns/1ns

module AccurateAddOneBit_tb;

    reg A;
    reg B;
    reg Cin;
    wire Cout;
    wire Sum;
    
    reg Sum_expct;
    reg Cout_expct;

    // Instantiate the Unit Under Test (UUT)
    AccurateAddOneBit uut (
        .A(A),
        .B(B),
        .Cin(Cin),
        .Cout(Cout),
        .Sum(Sum)
    );

    reg clk, reset; // clock and reset are internal
    reg[31:0] vectornum, errors; // bookkeeping variables
    reg[4:0] testvectors [7:0]; // array of testvectors

    // generate clock
    always // no sensitivity list
        begin
            clk = 1; #5;
            clk = 0; #5; // 1ns period
        end

    initial
        begin
            $dumpfile("adder.vcd"); // File with simulation results
            $dumpvars(0,AccurateAddOneBit_tb); // which variables are written to file
            $readmemb("tv_AccurateAddOneBit.tv", testvectors); // Read vectors
            vectornum = 0; errors = 0; // Initialize
            // Init
            A = 0;
            B = 0;
            Cin = 0;
            Sum_expct = 0;
            Cout_expct = 0;
            
            reset = 1;
            #10; reset = 0; // Apply reset wait
        end

    // Stimuli generation:
    // apply test vectors on rising edge of clk
    always @(posedge clk)
        begin
            #1; {A,B,Cin,Sum_expct,Cout_expct} = testvectors[vectornum]; // Apply inputs
        end

    // Response checker:
    // check results on falling edge of clk
    always @(negedge clk)
        if (~reset) // skip during reset
            begin
                if (Sum !== Sum_expct || Cout !== Cout_expct) // Check outputs
                    begin
                        $display("Error: inputs = %b", {A,B,Cin});
                        $display(" outputs = %b (%b exp)", {Sum,Cout}, {Sum_expct,Cout_expct});
                        errors = errors + 1;
                    end

                // increment array index and read next testvector
                vectornum = vectornum + 1;
                if (testvectors[vectornum] ===5'bx)
                    begin
                        $display("%d tests completed with %d errors", vectornum, errors);
                        $finish; // End simulation
                    end
            end
endmodule


/*
`timescale 1ns/1ns

module tb_SingleBit;
    reg A, B, Cin;
    wire Sum, Cout;
    
    AccurateAddOneBit uut (.A(A), .B(B), .Cin(Cin), .Sum(Sum), .Cout(Cout));
    
    initial begin
        $dumpfile("adder.vcd");
        $dumpvars(0, tb_SingleBit);

        // Init
        A = 0;
        B = 0;
        Cin = 0;

        #10 A=1'b0; B=1'b0; Cin=1'b0;
        #10 A=1'b0; B=1'b0; Cin=1'b1;

        #10 A=1'b0; B=1'b1; Cin=1'b0;
        #10 A=1'b0; B=1'b1; Cin=1'b1;
        
        #10 A=1'b1; B=1'b0; Cin=1'b0;
        #10 A=1'b1; B=1'b0; Cin=1'b1;
        
        #10 A=1'b1; B=1'b1; Cin=1'b0;
        #10 A=1'b1; B=1'b1; Cin=1'b1;
        
        #10 $finish;
    end
endmodule
*/

HW/ADD/adder.vcd
$date
	Thu Apr 25 12:57:27 2024
$end
$version
	Icarus Verilog
$end
$timescale
	1ns
$end
$scope module AccurateAddOneBit_tb $end
$var wire 1 ! Sum $end
$var wire 1 " Cout $end
$var reg 1 # A $end
$var reg 1 $ B $end
$var reg 1 % Cin $end
$var reg 1 & Cout_expct $end
$var reg 1 ' Sum_expct $end
$var reg 1 ( clk $end
$var reg 32 ) errors [31:0] $end
$var reg 1 * reset $end
$var reg 32 + vectornum [31:0] $end
$scope module uut $end
$var wire 1 # A $end
$var wire 1 $ B $end
$var wire 1 % Cin $end
$var wire 1 " Cout $end
$var wire 1 ! Sum $end
$upscope $end
$upscope $end
$enddefinitions $end
$comment Show the parameter values. $end
$dumpall
$end
#0
$dumpvars
b0 +
1*
b0 )
1(
0'
0&
0%
0$
0#
0"
0!
$end
#5
0(
#10
1(
0*
#15
b1 +
0(
#20
1(
#21
1!
1%
1'
#25
b10 +
0(
#30
1(
#31
1!
1$
0%
#35
b11 +
0(
#40
1(
#41
1"
0!
1%
0'
1&
#45
b100 +
0(
#50
1(
#51
0"
1!
1#
0$
0%
1'
0&
#55
b101 +
0(
#60
1(
#61
1"
0!
1%
0'
1&
#65
b110 +
0(
#70
1(
#71
0!
1$
0%
#75
b111 +
0(
#80
1(
#81
1!
1%
1'
#85
b1000 +
0(
