HW/ADD/OneBit/ApproxAddOneBit.v
/*
 *  Custom RISCV instruction for approximate multiplication
 *
 *  Copyright (C) 2024  Samir Hodzic, Veronica Kimelman, Paul Pölzl
 *
 *  Permission to use, copy, modify, and/or distribute this software for any
 *  purpose with or without fee is hereby granted, provided that the above
 *  copyright notice and this permission notice appear in all copies.
 *
 *  THE SOFTWARE IS PROVIDED "AS IS" AND THE AUTHOR DISCLAIMS ALL WARRANTIES
 *  WITH REGARD TO THIS SOFTWARE INCLUDING ALL IMPLIED WARRANTIES OF
 *  MERCHANTABILITY AND FITNESS. IN NO EVENT SHALL THE AUTHOR BE LIABLE FOR
 *  ANY SPECIAL, DIRECT, INDIRECT, OR CONSEQUENTIAL DAMAGES OR ANY DAMAGES
 *  WHATSOEVER RESULTING FROM LOSS OF USE, DATA OR PROFITS, WHETHER IN AN
 *  ACTION OF CONTRACT, NEGLIGENCE OR OTHER TORTIOUS ACTION, ARISING OUT OF
 *  OR IN CONNECTION WITH THE USE OR PERFORMANCE OF THIS SOFTWARE.
 *
 */

// Team 5 -> ApproxAdd2 implementation
module ApproxAddOneBit (A, B, Cin, Cout, Sum);

    input  wire A;
    input  wire B;
    input  wire Cin;
    output wire Cout;
    output wire Sum;

    assign Sum  = (!B) & ((!A) | (!Cin));
    assign Cout = !Sum;

endmodule

HW/ADD/OneBit/tb_OneBit.v
`timescale 1ns/1ns

`ifndef TEST_MODE
`define TEST_MODE 0
`endif 

`define ACC_TEST_VECTORS "tv_accurate.tv"
`define APPROX_TEST_VECTORS "tv_approx.tv"

`ifndef VCD_FILE
`define VCD_FILE "onebit.vcd"
`endif


module AddOneBit_tb;

    reg A;
    reg B;
    reg Cin;
    wire Cout;
    wire Sum;
    
    reg Sum_expct;
    reg Cout_expct;

    // Instantiate the Unit Under Test (UUT)
    if (`TEST_MODE == 0)
        AccurateAddOneBit uut (.A(A), .B(B), .Cin(Cin), .Cout(Cout), .Sum(Sum));
    else
        ApproxAddOneBit uut (.A(A), .B(B), .Cin(Cin), .Cout(Cout), .Sum(Sum));

    reg clk, reset; // clock and reset are internal
    reg[31:0] vectornum, errors; // bookkeeping variables
    reg[4:0] testvectors [7:0]; // array of testvectors

    // generate clock
    always // no sensitivity list
        begin
            clk = 1; #5;
            clk = 0; #5; // 1ns period
        end

    initial
        begin
            $dumpfile(`VCD_FILE); // File with simulation resuls
            $dumpvars(0, AddOneBit_tb); // Select which variables are written to file
            if (`TEST_MODE == 0)
                $readmemb(`ACC_TEST_VECTORS, testvectors); // Readvectors
            else
                $readmemb(`APPROX_TEST_VECTORS, testvectors); // Readvectors
            vectornum = 0; errors = 0; // Initialize
            // Init
            A = 0;
            B = 0;
            Cin = 0;
            Sum_expct = 0;
            Cout_expct = 0;
            
            reset = 1;
            #10; reset = 0; // Apply reset wait
        end

    // Stimuli generation:
    // apply test vectors on rising edge of clk
    always @(posedge clk)
        begin
            #1; {A,B,Cin,Sum_expct,Cout_expct} = testvectors[vectornum]; // Apply inputs
        end

    // Response checker:
    // check results on falling edge of clk
    always @(negedge clk)
        if (~reset) // skip during reset
            begin
                if (Sum !== Sum_expct || Cout !== Cout_expct) // Check outputs
                    begin
                        $display("Error: inputs = %b", {A,B,Cin});
                        $display(" outputs = %b (%b exp)", {Sum,Cout}, {Sum_expct,Cout_expct});
                        errors = errors + 1;
                    end

                // increment array index and read next testvector
                vectornum = vectornum + 1;
                if (testvectors[vectornum] ===5'bx)
                    begin
                        $display("%d tests completed with %d errors", vectornum, errors);
                        $finish; // End simulation
                    end
            end
endmodule

HW/ADD/AddOneBit.vcd
$date
	Thu May  2 09:50:13 2024
$end
$version
	Icarus Verilog
$end
$timescale
	1ns
$end
$scope module AddOneBit_tb $end
$var wire 1 ! Sum $end
$var wire 1 " Cout $end
$var reg 1 # A $end
$var reg 1 $ B $end
$var reg 1 % Cin $end
$var reg 1 & Cout_expct $end
$var reg 1 ' Sum_expct $end
$var reg 1 ( clk $end
$var reg 32 ) errors [31:0] $end
$var reg 1 * reset $end
$var reg 32 + vectornum [31:0] $end
$scope module uut $end
$var wire 1 # A $end
$var wire 1 $ B $end
$var wire 1 % Cin $end
$var wire 1 ! Sum $end
$var wire 1 " Cout $end
$upscope $end
$upscope $end
$enddefinitions $end
$comment Show the parameter values. $end
$dumpall
$end
#0
$dumpvars
b0 +
1*
b0 )
1(
0'
0&
0%
0$
0#
0"
1!
$end
#5
0(
#10
1(
0*
#11
1'
#15
b1 +
0(
#20
1(
#21
1%
#25
b10 +
0(
#30
1(
#31
1"
0!
1$
0%
0'
1&
#35
b11 +
0(
#40
1(
#41
1%
#45
b100 +
0(
#50
1(
#51
0"
1!
1#
0$
0%
1'
0&
#55
b101 +
0(
#60
1(
#61
1"
0!
1%
0'
1&
#65
b110 +
0(
#70
1(
#71
1$
0%
#75
b111 +
0(
#80
1(
#81
1%
#85
b1000 +
0(
