HW/ADD/AccurateAddOneBit.v
module AccurateAddOneBit (A, B, Cin, Cout, Sum);

    input  wire A;
    input  wire B;
    input  wire Cin;
    output wire Cout;
    output wire Sum;

    assign Sum  = (A ^ B) ^ Cin;
    assign Cout = (A & B) | ((A ^ B) & Cin);
    
endmodule

HW/ADD/AccurateAddMultiBit.v
// Accurate Multiple Bit Adder Implementation
module AccurateAddMultiBit (A, B, Cin, Sub, Sum, Cout);

    parameter bitWidth = 32;

    input  wire [bitWidth-1:0] A;
    input  wire [bitWidth-1:0] B;
    input  wire Cin;
    input  wire Sub; // '0' for adding, '1' for subtracting
    output wire [bitWidth-1:0] Sum;
    output wire Cout;

    wire [bitWidth-1:0] bIn; // true B signal, depending on whether you want to add or subtract
    wire [bitWidth:0] c_internal; // internal carry

    // calculate bIn depending on whether it is an addition or subtraction
    assign bIn = Sub ? ~B : B;

    // create multiple instances (each AccurateAddOneBit instance performs the addition for one bit position)
    genvar j;
    generate
        for (j = 0; j < bitWidth; j = j + 1) begin : adders
            // carry output from one bit is fed as the carry input to the next bit
            AccurateAddOneBit AccurateAddOneBit_Instance (.A(A[j]), .B(bIn[j]), .Sum(Sum[j]), .Cin(c_internal[j]), .Cout(c_internal[j+1]));
            //wire Cout_temp;
            //AccurateAddOneBit AccurateAddOneBit_Instance (.A(A[j]), .B(bIn[j]), .Sum(Sum[j]), .Cin(c_internal[j]), .Cout(Cout_temp));
            //assign carry_internal[i+1] = Cout_temp;
        end
    endgenerate

    assign c_internal[0] = Sub | Cin; // if Cin = '1' -> add operation or if Sub = '1' -> add operation (for two's complement)
    assign Cout = c_internal[bitWidth];

endmodule

HW/ADD/MultiBit/tb_MultiBit.v
`timescale 1ns/1ns

module AddMultiBit_tb;

    parameter bitWidth = 32;

    reg [bitWidth-1:0] A;
    reg [bitWidth-1:0] B;
    reg Cin;
    reg Sub;
    wire Cout;
    wire [bitWidth-1:0] Sum;
    
    reg [bitWidth-1:0] Sum_expct;
    reg Cout_expct;

    // Instantiate the Unit Under Test (UUT)
    AccurateAddMultiBit uut (.A(A), .B(B), .Cin(Cin), .Sub(Sub), .Cout(Cout), .Sum(Sum));
    //ApproxAddMultiBit uut (.A(A), .B(B), .Cin(Cin), .Sub(Sub), .Cout(Cout), .Sum(Sum));

    reg clk, reset; // clock and reset are internal
    reg[31:0] vectornum, errors; // bookkeeping variables
    reg[98:0] testvectors [0:5]; // array of testvectors

    // generate clock
    always // no sensitivity list
        begin
            clk = 1; #5;
            clk = 0; #5; // 1ns period
        end

    initial
        begin
            $dumpfile("AddMultiBit.vcd"); // File with simulation results
            $dumpvars(0, AddMultiBit_tb); // which variables are written to file
            $readmemb("tv_AccurateAddMultiBit.tv", testvectors); // Read vectors
            //$readmemb("tv_ApproxAddMultiBit.tv", testvectors); // Read vectors
            vectornum = 0; errors = 0; // Initialize
            // Init
            A = 0;
            B = 0;
            Cin = 0;
            Sum_expct = 0;
            Cout_expct = 0;
            
            reset = 1;
            #10; reset = 0; // Apply reset wait
        end

    // Stimuli generation:
    // apply test vectors on rising edge of clk
    always @(posedge clk)
        begin
            #1; {A,B,Cin,Sub,Sum_expct,Cout_expct} = testvectors[vectornum]; // Apply inputs
        end

    // Response checker:
    // check results on falling edge of clk
    always @(negedge clk)
        if (~reset) // skip during reset
            begin
                if (Sum !== Sum_expct || Cout !== Cout_expct) // Check outputs
                    begin
                        $display("Error: inputs: A=%h, B=%h, Cin=%b, Sub=%b", {A}, {B}, {Cin}, {Sub});
                        $display(" outputs: Sum=%h, Cout=%b (Exp: Sum=%h, Cout=%b)", {Sum}, {Cout}, {Sum_expct}, {Cout_expct});
                        errors = errors + 1;
                    end

                // increment array index and read next testvector
                vectornum = vectornum + 1;
                if (testvectors[vectornum] ===99'bx)
                    begin
                        $display("%d tests completed with %d errors", vectornum, errors);
                        $finish; // End simulation
                    end
            end
endmodule

HW/ADD/MultiBit/multibit.vcd
$date
	Thu May 16 12:12:24 2024
$end
$version
	Icarus Verilog
$end
$timescale
	1ns
$end
$scope module AddMultiBit_tb $end
$var wire 8 ! Sum [7:0] $end
$var wire 1 " Cout $end
$var parameter 32 # bitWidth $end
$var reg 8 $ A [7:0] $end
$var reg 8 % B [7:0] $end
$var reg 1 & Cin $end
$var reg 1 ' Cout_expct $end
$var reg 1 ( Sub $end
$var reg 8 ) Sum_expct [7:0] $end
$var reg 1 * clk $end
$var reg 32 + errors [31:0] $end
$var reg 1 , reset $end
$var reg 32 - vectornum [31:0] $end
$scope begin genblk1 $end
$scope module uut $end
$var wire 8 . A [7:0] $end
$var wire 8 / B [7:0] $end
$var wire 1 & Cin $end
$var wire 1 ( Sub $end
$var wire 9 0 c_internal [8:0] $end
$var wire 8 1 bIn [7:0] $end
$var wire 8 2 Sum [7:0] $end
$var wire 1 " Cout $end
$var parameter 32 3 bitWidth $end
$scope begin adders[0] $end
$var parameter 2 4 j $end
$scope module AccurateAddOneBit_Instance $end
$var wire 1 5 A $end
$var wire 1 6 B $end
$var wire 1 7 Cin $end
$var wire 1 8 Cout $end
$var wire 1 9 Sum $end
$upscope $end
$upscope $end
$scope begin adders[1] $end
$var parameter 2 : j $end
$scope module AccurateAddOneBit_Instance $end
$var wire 1 ; A $end
$var wire 1 < B $end
$var wire 1 = Cin $end
$var wire 1 > Cout $end
$var wire 1 ? Sum $end
$upscope $end
$upscope $end
$scope begin adders[2] $end
$var parameter 3 @ j $end
$scope module AccurateAddOneBit_Instance $end
$var wire 1 A A $end
$var wire 1 B B $end
$var wire 1 C Cin $end
$var wire 1 D Cout $end
$var wire 1 E Sum $end
$upscope $end
$upscope $end
$scope begin adders[3] $end
$var parameter 3 F j $end
$scope module AccurateAddOneBit_Instance $end
$var wire 1 G A $end
$var wire 1 H B $end
$var wire 1 I Cin $end
$var wire 1 J Cout $end
$var wire 1 K Sum $end
$upscope $end
$upscope $end
$scope begin adders[4] $end
$var parameter 4 L j $end
$scope module AccurateAddOneBit_Instance $end
$var wire 1 M A $end
$var wire 1 N B $end
$var wire 1 O Cin $end
$var wire 1 P Cout $end
$var wire 1 Q Sum $end
$upscope $end
$upscope $end
$scope begin adders[5] $end
$var parameter 4 R j $end
$scope module AccurateAddOneBit_Instance $end
$var wire 1 S A $end
$var wire 1 T B $end
$var wire 1 U Cin $end
$var wire 1 V Cout $end
$var wire 1 W Sum $end
$upscope $end
$upscope $end
$scope begin adders[6] $end
$var parameter 4 X j $end
$scope module AccurateAddOneBit_Instance $end
$var wire 1 Y A $end
$var wire 1 Z B $end
$var wire 1 [ Cin $end
$var wire 1 \ Cout $end
$var wire 1 ] Sum $end
$upscope $end
$upscope $end
$scope begin adders[7] $end
$var parameter 4 ^ j $end
$scope module AccurateAddOneBit_Instance $end
$var wire 1 _ A $end
$var wire 1 ` B $end
$var wire 1 a Cin $end
$var wire 1 b Cout $end
$var wire 1 c Sum $end
$upscope $end
$upscope $end
$upscope $end
$upscope $end
$upscope $end
$enddefinitions $end
$comment Show the parameter values. $end
$dumpall
b111 ^
b110 X
b101 R
b100 L
b11 F
b10 @
b1 :
b0 4
b1000 3
b1000 #
$end
#0
$dumpvars
xc
xb
xa
x`
0_
x]
x\
x[
xZ
0Y
xW
xV
xU
xT
0S
xQ
xP
xO
xN
0M
xK
xJ
xI
xH
0G
xE
xD
xC
xB
0A
x?
x>
x=
x<
0;
x9
x8
x7
x6
05
bx 2
bx 1
bx 0
b0 /
b0 .
b0 -
1,
b0 +
1*
b0 )
x(
0'
0&
b0 %
b0 $
x"
bx !
$end
#5
0*
#10
1*
0,
#11
0c
0]
0W
0Q
0K
0E
0?
0"
0a
0[
0U
0O
0I
0C
0=
0b
0\
0V
0P
0J
0D
0>
08
b0 !
b0 2
09
07
0`
0Z
0T
0N
0H
0B
0<
06
b0 0
b0 1
0(
b1 )
#15
b1 -
b1 +
0*
#20
1*
#21
b10 )
#25
b10 -
b10 +
0*
#30
1*
#31
b11 )
#35
b11 -
b11 +
0*
#40
1*
#41
b0 )
1'
#45
b100 -
b100 +
0*
#50
1*
#51
b1 )
#55
b101 -
b101 +
0*
#60
1*
#61
1=
1C
1I
1O
1U
1[
1a
1"
18
1>
1D
1J
1P
1V
1\
1b
b0 !
b0 2
09
17
0`
0Z
0T
0N
0H
0B
0<
06
15
1;
1A
1G
1M
1S
1Y
1_
b111111111 0
b0 1
b11111111 $
b11111111 .
b11111111 %
b11111111 /
1&
1(
b11111111 )
0'
#65
b110 -
b110 +
0*
